{
  "slug": "what-is-soil-food-web",
  "question": "what is soil food web",
  "pillar": "regenerative-agriculture",
  "title": "What Is the Soil Food Web? The Underground Ecosystem That Feeds Every Plant on Earth",
  "metaDescription": "The soil food web is a living community of billions of organisms that processes nutrients and delivers them to plant roots. Scotty breaks down how it works, why it matters more than fertilizer, and how to protect it in your garden.",
  "content": "# What Is the Soil Food Web? The Underground Ecosystem That Feeds Every Plant on Earth\n\nY'all, I want to talk about something that most gardeners never think about, but that is absolutely running the show underground in every healthy piece of soil on the planet.\n\nThe soil food web is the community of organisms — bacteria, fungi, protozoa, nematodes, earthworms, arthropods, and more — that live in the soil and interact with each other and with plant roots in an interconnected network of feeding relationships. It's called a food web because energy and nutrients flow through it as organisms eat and are eaten, just like an above-ground food web.\n\nHere's the key thing: the soil food web is what feeds plants. Not fertilizer. Not careful watering. The food web. The biological community in your soil processes organic matter, cycles nutrients, and delivers them to plant roots in the exact forms plants can use. Every natural ecosystem on Earth — every forest, every prairie, every wetland — operates this way. Agriculture that ignores the food web is basically fighting against the most sophisticated nutrient delivery system biology ever built.\n\n## Who's in the Soil Food Web\n\nLet me walk you through the cast of characters, because understanding who's in the system helps you understand how it works.\n\nAt the base are the decomposers — primarily bacteria and fungi. These are the organisms that break down organic matter. Dead leaves, root residues, animal waste, compost: all of it enters the food web through bacterial and fungal decomposition. They physically break these materials into smaller compounds, releasing nutrients from complex organic molecules and making them available to other organisms.\n\nBacteria are the dominant life form in most soils — they make up 70 to 90 percent of total microbial biomass. Fungal networks extend through the soil as hyphae, connecting plant roots to the broader soil system through mycorrhizal relationships. Both are the foundation of the food web's energy flow.\n\nOne trophic level up are the organisms that eat bacteria and fungi: protozoa, primarily. Amoebae, flagellates, and ciliates graze on bacterial populations, consuming enormous numbers of bacteria and releasing the nitrogen that was locked up in bacterial cells as ammonium — a form of nitrogen that plant roots can directly absorb. This is one of the primary ways nitrogen becomes plant-available in living soil. Not synthetic fertilizer. Protozoa eating bacteria.\n\nNematodes occupy a similar role. Some eat bacteria. Others eat fungi. Still others eat protozoa or other nematodes. Each time a nematode eats, it releases nutrients in forms available to the next level of the web. Nematodes are also prey for arthropods — mites, springtails, beetles — and those arthropods in turn support larger organisms.\n\nAt the top of the soil food web are earthworms, ground beetles, ants, and the organisms that eat them. Earthworms do enormous physical work in the soil: consuming organic matter, digesting it with the help of their own gut bacteria, and depositing nutrient-rich casts that are highly available to plant roots. Earthworm castings are among the best plant amendments available — basically because they represent organic matter that has been through multiple passes of biological processing in the food web.\n\n## How Nutrients Flow Through the System\n\nOrganic matter enters the soil as plant residues, animal waste, and decomposing organisms. Bacteria and fungi begin breaking it down — decomposing complex molecules into simpler ones. As they do this, nutrients are released from the organic compounds and temporarily held in bacterial and fungal cells.\n\nWhen protozoa and nematodes eat those bacteria and fungi, they consume more nitrogen than they need for their own growth. The excess nitrogen is excreted as ammonium, right in the root zone of the plant. The plant roots absorb it. This is the nutrient transfer mechanism — it happens in microdoses, continuously, right where the roots are, in exactly the forms plants can use.\n\nThis is fundamentally different from applying synthetic fertilizer. When you dump nitrogen fertilizer on your soil, you're flooding the system with more nitrogen than plants can immediately use. The excess leaches into groundwater or volatilizes into the atmosphere. It's wasteful and it damages aquatic ecosystems downstream.\n\nThe biological pathway delivers nutrients slowly, continuously, and in the right place. The food web is a precision nutrient delivery system that conventional agriculture bypasses at enormous cost — financially, environmentally, and in terms of long-term soil health.\n\nA key concept here is what I call the decay cycle. Organic matter in — decomposition — nutrients released — plants grow — plant material back in — decomposition again. Round and round. The food web is the engine that runs that cycle. When the food web is intact and active, the cycle runs continuously and your soil gets more productive over time. When the food web is depleted or destroyed, the cycle breaks and you're back to inputs.\n\n## What Healthy Soil Food Web Looks Like\n\nHere's how to tell whether your soil has an active food web.\n\nFirst: aggregates. Healthy living soil with an active food web has what's called aggregate structure — small clumps of soil particles held together by fungal hyphae, bacterial secretions, and organic matter. These aggregates give soil its crumbly, spongy texture. They create the pore spaces that hold water and allow air circulation. If your soil has no aggregates — if it's powdery dry or plasticky wet — the food web is depleted.\n\nSecond: earthworm presence. Earthworms require moisture, organic matter, and an active microbial community to thrive. Dig a cubic foot of healthy soil and you should find at least a few earthworms. If you find dozens, you've got something working.\n\nThird: smell. Active soil bacteria — particularly actinobacteria — produce geosmin, the compound responsible for that earthy smell of fresh soil after rain. Living soil smells alive. Degraded soil smells like nothing, or sometimes sour if anaerobic conditions have developed.\n\nFourth: plant vigor. Plants growing in an active food web are typically more vigorous, more disease-resistant, and more flavorful than plants grown in biologically degraded soil with synthetic inputs. The food web delivers micronutrients and protective compounds that fertilizer doesn't.\n\n## How to Support the Soil Food Web\n\nAdd organic matter consistently. Compost, mulch, cover crop residues — these are the food inputs that the base of the food web runs on. Without organic matter entering the system, the food web has nothing to process. The more diverse the organic matter, the more diverse the biological community it supports.\n\nReduce or eliminate tillage. Tillage physically destroys fungal networks, disrupts the layered ecology of the soil community, and spikes and crashes microbial activity in a way that depletes organic matter. Every tillage pass is a disruption to your food web.\n\nKeep living roots in the ground. Plant roots produce exudates — sugars and other compounds — that bacteria and fungi feed on. A bed with no living roots is starving the food web. Cover crops between main crops keep the exudate supply running.\n\nStop using inputs that kill soil organisms. Fungicides kill fungi, including mycorrhizal fungi. Some herbicides disrupt bacterial communities. Synthetic fertilizer suppresses the biological relationships that make nutrient cycling work. Every chemical intervention in your garden should be evaluated against the question: what does this do to the food web?\n\nThe soil food web is not a theory. It's the engine that has been running terrestrial agriculture since the first land plants colonized the Earth. Build it and protect it, and your soil will take care of your plants.\n\n---\n\n## Sources\n\n- [Soil Food Web — Wikipedia](https://en.wikipedia.org/wiki/Soil_food_web)\n- [The Soil Food Web and Nutrient Cycling — AHDB](https://ahdb.org.uk/knowledge-library/the-soil-food-web-and-nutrient-cycling)\n- [Introduction to the Soil Food Web — Urban Worm Company](https://urbanwormcompany.com/soil-food-web-intro-decomposer-filter/)\n- [Soil Food Webs and Their Role in Soil Health — Farm to Garden Organics](https://farmtogarden.ca/organic-education/soil-food-webs-and-their-role-in-soil-health/)\n- [Soil Food Web — ScienceDirect Topics](https://www.sciencedirect.com/topics/agricultural-and-biological-sciences/soil-food-web)\n",
  "sources": [
    {
      "title": "Soil Food Web",
      "url": "https://en.wikipedia.org/wiki/Soil_food_web",
      "publisher": "Wikipedia"
    },
    {
      "title": "The Soil Food Web and Nutrient Cycling",
      "url": "https://ahdb.org.uk/knowledge-library/the-soil-food-web-and-nutrient-cycling",
      "publisher": "AHDB — Agriculture and Horticulture Development Board"
    },
    {
      "title": "Introduction to the Soil Food Web",
      "url": "https://urbanwormcompany.com/soil-food-web-intro-decomposer-filter/",
      "publisher": "Urban Worm Company"
    },
    {
      "title": "Soil Food Webs and Their Role in Soil Health",
      "url": "https://farmtogarden.ca/organic-education/soil-food-webs-and-their-role-in-soil-health/",
      "publisher": "Farm to Garden Organics"
    },
    {
      "title": "Soil Food Web Overview",
      "url": "https://www.sciencedirect.com/topics/agricultural-and-biological-sciences/soil-food-web",
      "publisher": "ScienceDirect Topics"
    }
  ],
  "scottyQuotes": [
    "The soil food web feeds plants. Not fertilizer. Not careful watering. The biological community in the soil processes nutrients and delivers them to roots in the exact forms plants can use.",
    "When protozoa eat bacteria, they excrete the excess nitrogen as ammonium — right in the root zone, right where the plant needs it. That's precision nutrient delivery that no synthetic fertilizer can match.",
    "The decay cycle is what I call it: organic matter in, decomposition, nutrients released, plants grow, plant material back in, decomposition again. The food web is the engine that runs this cycle."
  ],
  "wordCount": 1420
}
